CHANGES.txt
CONTRIBUTORS.txt
MANIFEST.in
README.txt
setup.cfg
setup.py
collective/__init__.py
collective.calameo.egg-info/PKG-INFO
collective.calameo.egg-info/SOURCES.txt
collective.calameo.egg-info/dependency_links.txt
collective.calameo.egg-info/entry_points.txt
collective.calameo.egg-info/namespace_packages.txt
collective.calameo.egg-info/not-zip-safe
collective.calameo.egg-info/requires.txt
collective.calameo.egg-info/top_level.txt
collective/calameo/README.txt
collective/calameo/__init__.py
collective/calameo/config.py
collective/calameo/configure.zcml
collective/calameo/browser/__init__.py
collective/calameo/browser/calameomacros.pt
collective/calameo/browser/calameoview.pt
collective/calameo/browser/calameoview.py
collective/calameo/browser/configure.zcml
collective/calameo/content/__init__.py
collective/calameo/content/calameopdf.py
collective/calameo/content/configure.zcml
collective/calameo/interfaces/__init__.py
collective/calameo/interfaces/calameopdf.py
collective/calameo/locales/collective.calameo.pot
collective/calameo/locales/rebuild.sh
collective/calameo/locales/it/LC_MESSAGES/collective.calameo.mo
collective/calameo/locales/it/LC_MESSAGES/collective.calameo.po
collective/calameo/profiles/default/factorytool.xml
collective/calameo/profiles/default/metadata.xml
collective/calameo/profiles/default/portlets.xml
collective/calameo/profiles/default/rolemap.xml
collective/calameo/profiles/default/types.xml
collective/calameo/profiles/default/types/CalameoPDF.xml
collective/calameo/tests/__init__.py
collective/calameo/tests/base.py
collective/calameo/tests/contentype_base_tests.txt
collective/calameo/tests/test_doctest.py
docs/HISTORY.txt
docs/INSTALL.txt
docs/LICENSE.GPL
docs/LICENSE.txt