Metadata-Version: 1.0
Name: collective.calameo
Version: 0.1
Summary: Publish your PDF document in Plone with Calameo
Home-page: http://plone.org/products/collective.calameo
Author: Giorgio Borelli
Author-email: giorgio@giorgioborelli.it
License: GPL
Platform: UNKNOWN
Classifier: Framework :: Plone
Classifier: Intended Audience :: Developers
Classifier: Topic :: Software Development :: Libraries :: Python Modules
Classifier: License :: OSI Approved :: GNU General Public License (GPL)
